virtcoilphase/__init__.py
virtcoilphase/virtcoilphase.py
virtcoilphase/examples/__init__.py
virtcoilphase/examples/simple.py
virtcoilphase-0.1.0.dist-info/LICENSE
virtcoilphase-0.1.0.dist-info/METADATA
virtcoilphase-0.1.0.dist-info/WHEEL
virtcoilphase-0.1.0.dist-info/top_level.txt
virtcoilphase-0.1.0.dist-info/RECORD
