Metadata-Version: 2.1
Name: virtcoilphase
Version: 0.1.0
Summary: Virtual reference coil method to determine phase distribution
Home-page: https://github.com/mckib2/virtcoilphase
Author: Nicholas McKibben
Author-email: nicholas.bgp@gmail.com
License: GPLv3
Platform: UNKNOWN
Requires-Python: >=3.6
Requires-Dist: numpy (>=1.17.2)
Requires-Dist: scipy (>=1.3.1)
Requires-Dist: matplotlib (>=3.1.1)
Requires-Dist: tqdm (>=4.36.1)
